{
  "$schema": "https://developer.microsoft.com/json-schemas/fabric/item/report/definition/visualContainer/2.6.0/schema.json",
  "name": "d4d19fff633cbd569b8c",
  "position": {
    "x": 552,
    "y": 88,
    "z": 19000,
    "height": 136,
    "width": 196,
    "tabOrder": 19000
  },
  "visual": {
    "visualType": "clusteredBarChart",
    "query": {
      "queryState": {
        "Y": {
          "projections": [
            {
              "field": {
                "Measure": {
                  "Expression": {
                    "SourceRef": {
                      "Entity": "MeasureTable"
                    }
                  },
                  "Property": "Gain"
                }
              },
              "queryRef": "MeasureTable.Gain",
              "nativeQueryRef": "Gain"
            }
          ]
        }
      },
      "sortDefinition": {
        "sort": [
          {
            "field": {
              "Measure": {
                "Expression": {
                  "SourceRef": {
                    "Entity": "MeasureTable"
                  }
                },
                "Property": "Gain"
              }
            },
            "direction": "Descending"
          }
        ],
        "isDefaultSort": true
      }
    },
    "objects": {
      "y1AxisReferenceLine": [
        {
          "properties": {
            "show": {
              "expr": {
                "Literal": {
                  "Value": "true"
                }
              }
            },
            "displayName": {
              "expr": {
                "Literal": {
                  "Value": "'Y-Axis Constant Line 1'"
                }
              }
            },
            "value": {
              "expr": {
                "Measure": {
                  "Expression": {
                    "SourceRef": {
                      "Entity": "MeasureTable"
                    }
                  },
                  "Property": "Gain BM"
                }
              }
            },
            "transparency": {
              "expr": {
                "Literal": {
                  "Value": "0D"
                }
              }
            },
            "width": {
              "expr": {
                "Literal": {
                  "Value": "2D"
                }
              }
            },
            "style": {
              "expr": {
                "Literal": {
                  "Value": "'solid'"
                }
              }
            },
            "dataLabelShow": {
              "expr": {
                "Literal": {
                  "Value": "true"
                }
              }
            },
            "dataLabelVerticalPosition": {
              "expr": {
                "Literal": {
                  "Value": "'above'"
                }
              }
            },
            "lineColor": {
              "solid": {
                "color": {
                  "expr": {
                    "Literal": {
                      "Value": "'#b1e1f4'"
                    }
                  }
                }
              }
            },
            "dataLabelColor": {
              "solid": {
                "color": {
                  "expr": {
                    "ThemeDataColor": {
                      "ColorId": 5,
                      "Percent": 0.2
                    }
                  }
                }
              }
            }
          },
          "selector": {
            "id": "1"
          }
        }
      ],
      "valueAxis": [
        {
          "properties": {
            "show": {
              "expr": {
                "Literal": {
                  "Value": "false"
                }
              }
            }
          }
        }
      ],
      "labels": [
        {
          "properties": {
            "show": {
              "expr": {
                "Literal": {
                  "Value": "true"
                }
              }
            },
            "labelPosition": {
              "expr": {
                "Literal": {
                  "Value": "'InsideEnd'"
                }
              }
            },
            "fontSize": {
              "expr": {
                "Literal": {
                  "Value": "9D"
                }
              }
            }
          }
        }
      ],
      "categoryAxis": [
        {
          "properties": {
            "maxMarginFactor": {
              "expr": {
                "Literal": {
                  "Value": "20L"
                }
              }
            },
            "innerPadding": {
              "expr": {
                "Literal": {
                  "Value": "0L"
                }
              }
            },
            "show": {
              "expr": {
                "Literal": {
                  "Value": "true"
                }
              }
            }
          }
        }
      ],
      "dataPoint": [
        {
          "properties": {
            "borderShow": {
              "expr": {
                "Literal": {
                  "Value": "false"
                }
              }
            }
          }
        }
      ]
    },
    "drillFilterOtherVisuals": true
  }
}